odoo/addons/l10n_br_hr_contract/README.rst
odoo/addons/l10n_br_hr_contract/__init__.py
odoo/addons/l10n_br_hr_contract/__manifest__.py
odoo/addons/l10n_br_hr_contract/data/hr_contract_admission_type_data.xml
odoo/addons/l10n_br_hr_contract/data/hr_contract_labor_bond_type_data.xml
odoo/addons/l10n_br_hr_contract/data/hr_contract_labor_regime_data.xml
odoo/addons/l10n_br_hr_contract/data/hr_contract_notice_termination_data.xml
odoo/addons/l10n_br_hr_contract/data/hr_contract_resignation_cause_data.xml
odoo/addons/l10n_br_hr_contract/data/hr_contract_salary_unit_data.xml
odoo/addons/l10n_br_hr_contract/i18n/l10n_br_hr_contract.pot
odoo/addons/l10n_br_hr_contract/i18n/pt_BR.po
odoo/addons/l10n_br_hr_contract/models/__init__.py
odoo/addons/l10n_br_hr_contract/models/hr_contract.py
odoo/addons/l10n_br_hr_contract/models/hr_contract_admission_type.py
odoo/addons/l10n_br_hr_contract/models/hr_contract_labor_bond_type.py
odoo/addons/l10n_br_hr_contract/models/hr_contract_labor_regime.py
odoo/addons/l10n_br_hr_contract/models/hr_contract_labor_resignation_cause.py
odoo/addons/l10n_br_hr_contract/models/hr_contract_labor_salary_unit.py
odoo/addons/l10n_br_hr_contract/models/hr_contract_notice_termination.py
odoo/addons/l10n_br_hr_contract/models/hr_data_abstract.py
odoo/addons/l10n_br_hr_contract/readme/CONFIGURE.md
odoo/addons/l10n_br_hr_contract/readme/CONTRIBUTORS.md
odoo/addons/l10n_br_hr_contract/readme/DESCRIPTION.md
odoo/addons/l10n_br_hr_contract/readme/HISTORY.md
odoo/addons/l10n_br_hr_contract/readme/INSTALL.md
odoo/addons/l10n_br_hr_contract/readme/ROADMAP.md
odoo/addons/l10n_br_hr_contract/readme/USAGE.md
odoo/addons/l10n_br_hr_contract/security/ir.model.access.csv
odoo/addons/l10n_br_hr_contract/static/description/icon.png
odoo/addons/l10n_br_hr_contract/static/description/index.html
odoo/addons/l10n_br_hr_contract/tests/__init__.py
odoo/addons/l10n_br_hr_contract/tests/test_l10n_br_hr_contract.py
odoo/addons/l10n_br_hr_contract/views/hr_contract_view.xml
odoo14_addon_l10n_br_hr_contract-14.0.1.0.1.dist-info/METADATA
odoo14_addon_l10n_br_hr_contract-14.0.1.0.1.dist-info/WHEEL
odoo14_addon_l10n_br_hr_contract-14.0.1.0.1.dist-info/top_level.txt
odoo14_addon_l10n_br_hr_contract-14.0.1.0.1.dist-info/RECORD
