Metadata-Version: 2.1
Name: odoo14-addon-l10n_br_hr_contract
Version: 14.0.1.0.1
Requires-Python: >=3.6
Requires-Dist: erpbrasil.base
Requires-Dist: odoo14-addon-l10n_br_hr
Requires-Dist: odoo>=14.0a,<14.1dev
Summary: Brazilian Localization HR Contract
Home-page: https://github.com/OCA/l10n-brazil
License: AGPL-3
Author: KMEE, Odoo Community Association (OCA)
Author-email: support@odoo-community.org
Classifier: Programming Language :: Python
Classifier: Framework :: Odoo
Classifier: Framework :: Odoo :: 14.0
Classifier: License :: OSI Approved :: GNU Affero General Public License v3
